[
  {
    "card_name": "emiel regis rohellec terzieff",
    "faction": "neutral",
    "row": "melee",
    "strength" : 5,
    "card_type": "unit",
    "ability": "none"
  },
  {
    "card_name": "geralt of rivia",
    "faction": "neutral",
    "row": "melee",
    "strength": 15,
    "card_type": "unit",
    "ability": "hero"
  },
  {
    "card_name": "zoltan chivay",
    "faction": "neutral",
    "row": "melee",
    "strength": 5,
    "card_type": "unit",
    "ability": "none"
  },
  {
    "card_name": "vesemir",
    "faction": "neutral",
    "row": "melee",
    "strength": 6,
    "card_type": "unit",
    "ability": "none"
  },
  {
    "card_name": "philippa Eilhart",
    "faction": "northern realms",
    "row": "range",
    "strength": 10,
    "card_type": "unit",
    "ability": "hero"
  },
  {
    "card_name": "esterad thyssen",
    "faction": "northern realms",
    "row": "range",
    "strength": 10,
    "card_type": "unit",
    "ability": "hero"
  },
  {
    "card_name": "john natalis",
    "faction": "northern realms",
    "row": "melee",
    "strength": 10,
    "card_type": "unit",
    "ability": "hero"
  },
  {
    "card_name": "moruran voorhis",
    "faction": "nilfgaardian",
    "row": "siege",
    "strength": 10,
    "card_type": "unit",
    "ability": "hero"
  },
  {
    "card_name": "menno coehoorn",
    "faction": "nilfgaardian",
    "row": "melee",
    "strength": 10,
    "card_type": "unit",
    "ability": "medic"
  },
  {
    "card_name": "redanian foot soldier",
    "faction": "northern realms",
    "row": "melee",
    "strength": 1,
    "card_type": "unit",
    "ability": "none"
  },
  {
    "card_name": "sigismund dijkstra",
    "faction": "northern realms",
    "row": "melee",
    "strength": 4,
    "card_type": "unit",
    "ability": "spy"
  },
  {
    "card_name": "vernon roche",
    "faction": "northern realms",
    "row": "melee",
    "strength": 10,
    "card_type": "unit",
    "ability": "hero"
  },
  {
    "card_name": "trebuchet",
    "faction": "northern realms",
    "row": "siege",
    "strength": 6,
    "card_type": "unit",
    "ability": "none"

  },
  {
    "card_name": "blue stripes commando",
    "faction": "northern realms",
    "row": "melee",
    "strength": 4,
    "card_type": "unit",
    "ability": "tight bound"
  },
  {
    "card_name": "dethmold",
    "faction": "northern realms",
    "row": "range",
    "strength": 6,
    "card_type": "unit",
    "ability": "none"
  },
  {
    "card_name": "assire van anahid",
    "faction": "nilfgaardian",
    "row": "range",
    "strength": 6,
    "card_type": "unit",
    "ability": "none"
  },
  {
    "card_name": "imprea brigade guard",
    "faction": "nilfgaardian",
    "row": "melee",
    "strength": 3,
    "card_type": "unit",
    "ability": "tight bound"
  },
  {
    "card_name": "siege engineer",
    "faction": "nilfgaardian",
    "row": "siege",
    "strength": 6,
    "card_type": "unit",
    "ability": "none"
  },
  {
    "card_name": "tibor eggebracht",
    "faction": "nilfgaardian",
    "row": "range",
    "strength": 10,
    "card_type": "unit",
    "ability": "hero"
  },
  {
    "card_name": "vattier de rideaux",
    "faction": "nilfgaardian",
    "row": "melee",
    "strength": 4,
    "card_type": "unit",
    "ability": "spy"
  },
  {
    "card_name": "puttkammer",
    "faction": "nilfgaardian",
    "row": "range",
    "strength": 3,
    "card_type": "unit",
    "ability": "none"
  },
  {
    "card_name": "commander's horn",
    "faction": "neutral",
    "row": "none",
    "strength": 0,
    "card_type": "buff",
    "ability": "horn"
  },
  {
    "card_name": "scorch",
    "faction": "neutral",
    "row": "none",
    "strength": 0,
    "card_type": "buff",
    "ability": "scorch"
  },
  {
    "card_name":"torrential rain",
    "faction": "neutral",
    "row": "none",
    "strength": 0,
    "card_type": "weather",
    "ability": "rain"
  },
  {
    "card_name": "biting frost",
    "faction": "neutral",
    "row": "none",
    "strength": 0,
    "card_type": "weather",
    "ability": "frost"
  },
  {
    "card_name": "clear weather",
    "faction": "neutral",
    "row": "none",
    "strength": 0,
    "card_type": "weather",
    "ability": "clear weather"
  }
]
